envwrap/__init__.py
envwrap/py.typed
envwrap/resources/.gitkeep
envwrap-0.1.0.dist-info/LICENSE
envwrap-0.1.0.dist-info/METADATA
envwrap-0.1.0.dist-info/WHEEL
envwrap-0.1.0.dist-info/RECORD
