Metadata-Version: 2.1
Name: envwrap
Version: 0.1.0
Summary: 🚀 Override function defaults with environment variables
Home-page: https://github.com/regulad/envwrap
License: MIT
Author: Parker Wahle
Author-email: regulad@regulad.xyz
Requires-Python: >=3.8,<4.0
Classifier: Development Status :: 4 - Beta
Classifier: License :: OSI Approved :: MIT License
Classifier: Programming Language :: Python :: 3
Classifier: Programming Language :: Python :: 3.8
Classifier: Programming Language :: Python :: 3.9
Classifier: Programming Language :: Python :: 3.10
Classifier: Programming Language :: Python :: 3.11
Classifier: Programming Language :: Python :: 3.12
Requires-Dist: typing-extensions (>=4.12.2,<5.0.0)
Project-URL: Changelog, https://github.com/regulad/envwrap/releases
Project-URL: Documentation, https://envwrap.readthedocs.io
Project-URL: Repository, https://github.com/regulad/envwrap
